{
    "fixed_count": 10,
    "generated_count": 30,
    "fixed_runtime_seconds": 753.23,
    "generated_runtime_seconds": 1636.15,
    "best_fixed": {
        "Strategy ID": "supertrend_ema_atr",
        "Strategy Name": "SuperTrend + EMA + ATR SL",
        "Strategy Source": "FIXED",
        "Template Type": "fixed",
        "Pair": "SOLUSDT",
        "Timeframe": "15m",
        "SL %": 1.5,
        "TP %": 3.0,
        "ROI %": 45.55,
        "Profit Factor": 1.07,
        "Total PnL %": 48.0,
        "Win Rate %": 35.68,
        "Max Drawdown %": -27.09,
        "Trades": 454.0,
        "Expectancy": 10.03,
        "Runtime Seconds": 40.91,
        "PF Score": 13.375,
        "PnL Score": 24.0,
        "Win Score": 11.893333333333334,
        "DD Score": 6.455,
        "Trade Score": 10.0,
        "Overall Score": 65.72333333333333
    },
    "best_generated": {
        "Strategy ID": "HYB001_EMA50_100_RSI14_VOL1P2_SL1P5_TP3P0",
        "Strategy Name": "Generated Hybrid EMA 50/100 RSI 14 Vol 1.2",
        "Strategy Source": "GENERATED",
        "Template Type": "hybrid",
        "Pair": "ETHUSDT",
        "Timeframe": "15m",
        "SL %": 2.0,
        "TP %": 3.0,
        "ROI %": 72.34,
        "Profit Factor": 1.19,
        "Total PnL %": 62.0,
        "Win Rate %": 45.08,
        "Max Drawdown %": -20.37,
        "Trades": 244.0,
        "Expectancy": 29.65,
        "Runtime Seconds": 40.9,
        "PF Score": 14.875,
        "PnL Score": 25.0,
        "Win Score": 15.026666666666666,
        "DD Score": 9.815000000000001,
        "Trade Score": 10.0,
        "Overall Score": 74.71666666666667
    },
    "improvement": {
        "roi_pct": 26.79,
        "profit_factor": 0.12,
        "win_rate_pct": 9.4,
        "max_drawdown_pct": 6.72,
        "overall_score": 8.99
    }
}